Register File/RegisterFile.v
module register_file (
    input [4:0] reg_write,
    input [31:0] write_data,
    input [4:0] read1,
    input [4:0] read2,
    output reg [31:0] read_data1,
    output reg [31:0] read_data2,
    input writeenable,
    input clk,
    input rst
);

reg [31:0] regs [0:31];
integer i;

always @(posedge clk) begin
    if (rst) begin
        // Reset all registers to zero
        for (i = 0; i < 32; i++) begin
            regs[i] <= 0;
        end
    end else begin
        // Write to register file if write enable is asserted
        if (writeenable) begin
            if (reg_write != 0) begin
                #1 regs[reg_write] <= write_data;
            end
        end
        
        // Read from register file
        #2 read_data1 <= regs[read1];
        #2 read_data2 <= regs[read2];
    end
end

endmodule

Register File/RegisterTestBed.v
`include "RegisterFile.v"
`timescale 1ns/1ps

module register_file_tb;

  // Declare the DUT (device under test)
  reg [4:0] reg_write;
  reg [31:0] write_data;
  reg [4:0] read1, read2;
  wire [31:0] read_data1, read_data2;
  reg writeenable;
  reg clk, rst;
  
  register_file dut (
    .reg_write(reg_write),
    .write_data(write_data),
    .read1(read1),
    .read2(read2),
    .read_data1(read_data1),
    .read_data2(read_data2),
    .writeenable(writeenable),
    .clk(clk),
    .rst(rst)
  );
  
  // Toggle the clock signal
  always #5 clk = ~clk;
  
  // Initialize testbench inputs
  initial begin
    // Reset the DUT
    rst = 1;
    #10 rst = 0;
    
    // Random write and read operations
    repeat(1000) begin
      // Random write operation
      if ($random % 2 == 0) begin
        reg_write = $random % 32;
        write_data = $random;
        writeenable = 1;
        #10;
      end
      
      // Random read operation
      read1 = $random % 32;
      read2 = $random % 32;
      #10;
    end
    
    // End simulation
    #10 $finish;
  end
  
  // Dump waveform into a VCD file
  initial begin
    $dumpfile("register_file_waveform.vcd");
    $dumpvars(0, register_file_tb);
    #10;
  end
  
endmodule

Register File/register_file_waveform.vcd
$date
	Thu Apr 20 09:37:59 2023
$end
$version
	Icarus Verilog
$end
$timescale
	1ps
$end
$scope module register_file_tb $end
$var wire 32 ! read_data2 [31:0] $end
$var wire 32 " read_data1 [31:0] $end
$var reg 1 # clk $end
$var reg 5 $ read1 [4:0] $end
$var reg 5 % read2 [4:0] $end
$var reg 5 & reg_write [4:0] $end
$var reg 1 ' rst $end
$var reg 32 ( write_data [31:0] $end
$var reg 1 ) writeenable $end
$scope module dut $end
$var wire 1 # clk $end
$var wire 5 * read1 [4:0] $end
$var wire 5 + read2 [4:0] $end
$var wire 5 , reg_write [4:0] $end
$var wire 1 ' rst $end
$var wire 32 - write_data [31:0] $end
$var wire 1 ) writeenable $end
$var reg 32 . read_data1 [31:0] $end
$var reg 32 / read_data2 [31:0] $end
$var integer 32 0 i [31:0] $end
$upscope $end
$upscope $end
$enddefinitions $end
#0
$dumpvars
bx 0
bx /
bx .
bx -
bx ,
bx +
bx *
x)
bx (
1'
bx &
bx %
bx $
x#
bx "
bx !
$end
#10000
1)
b10000100100001001101011000001001 (
b10000100100001001101011000001001 -
b1 &
b1 ,
0'
#20000
b1101 %
b1101 +
b11 $
b11 *
#30000
b10010 %
b10010 +
b101 $
b101 *
#40000
b10110 %
b10110 +
b1101 $
b1101 *
#50000
b1100 %
b1100 +
#60000
b101 %
b101 +
b110 $
b110 *
#70000
b10111011110100100111001001110111 (
b10111011110100100111001001110111 -
b101 &
b101 ,
#80000
b1111 %
b1111 +
b10010 $
b10010 *
#90000
b11110100000000000111101011101000 (
b11110100000000000111101011101000 -
b1110 &
b1110 ,
#100000
b11100 %
b11100 +
b101 $
b101 *
#110000
b101 %
b101 +
b1101 $
b1101 *
#120000
b0 %
b0 +
b1010 $
b1010 *
#130000
b11001110110011001100110010011101 (
b11001110110011001100110010011101 -
b1010 &
b1010 ,
#140000
b10011 %
b10011 +
b10110 $
b10110 *
#150000
b1011 %
b1011 +
b10011 $
b10011 *
#160000
b1110 %
b1110 +
b10 $
b10 *
#170000
b11 %
b11 +
b1111 $
b1111 *
#180000
b10011110001100010100110000111100 (
b10011110001100010100110000111100 -
#190000
b1010 %
b1010 +
b10010 $
b10010 *
#200000
b11000 %
b11000 +
b11000 $
b11000 *
#210000
b10110 %
b10110 +
b1011 $
b1011 *
#220000
b11011110011101010000001010111100 (
b11011110011101010000001010111100 -
b1110 &
b1110 ,
#230000
b1011 %
b1011 +
b1010 $
b1010 *
#240000
b1111 %
b1111 +
b101 $
b101 *
#250000
b11110 %
b11110 +
b11010 $
b11010 *
#260000
b11001 %
b11001 +
b10001 $
b10001 *
#270000
b1001111101000010101010110011111 (
b1001111101000010101010110011111 -
b1100 &
b1100 ,
#280000
b11000 %
b11000 +
b1111 $
b1111 *
#290000
b11100 %
b11100 +
b11111 $
b11111 *
#300000
b1001 %
b1001 +
b1001 $
b1001 *
#310000
b10101000110001111111110001010001 (
b10101000110001111111110001010001 -
b10111 &
b10111 ,
#320000
b1100 %
b1100 +
b10110 $
b10110 *
#330000
b10111011100000100101101001110111 (
b10111011100000100101101001110111 -
b1000 &
b1000 ,
#340000
b10010 %
b10010 +
b11101 $
b11101 *
#350000
b11100110110011110011100111001 (
b11100110110011110011100111001 -
b1101 &
b1101 ,
#360000
b10011 %
b10011 +
b11111 $
b11111 *
#370000
b11011 %
b11011 +
b11000 $
b11000 *
#380000
b1010 %
b1010 +
b11111 $
b11111 *
#390000
b11000111000110100000110010001110 (
b11000111000110100000110010001110 -
b110 &
b110 ,
#400000
b11010 %
b11010 +
b11100 $
b11100 *
#410000
b11010001100010111011010010100011 (
b11010001100010111011010010100011 -
b10011 &
b10011 ,
#420000
b10011 %
b10011 +
b1111 $
b1111 *
#430000
b10111 %
b10111 +
b100 $
b100 *
#440000
b11010 %
b11010 +
b110 $
b110 *
#450000
b1101 $
b1101 *
#460000
b11111 %
b11111 +
b10101 $
b10101 *
#470000
b10000 %
b10000 +
b100 $
b100 *
#480000
b111011011111100111100001110 (
b111011011111100111100001110 -
b1011 &
b1011 ,
#490000
b11010 %
b11010 +
b11100 $
b11100 *
#500000
b10110 %
b10110 +
b11 $
b11 *
#510000
b10000101001100010011010000001010 (
b10000101001100010011010000001010 -
b111 &
b111 ,
#520000
b11000 %
b11000 +
b10110 $
b10110 *
#530000
b10100 %
b10100 +
b11000 $
b11000 *
#540000
b11001 %
b11001 +
b100 $
b100 *
#550000
b1101 $
b1101 *
#560000
b1010 %
b1010 +
b10110 $
b10110 *
#570000
b10100011000001110001101001000110 (
b10100011000001110001101001000110 -
b10101 &
b10101 ,
#580000
b10111 %
b10111 +
b100 $
b100 *
#590000
b1000 %
b1000 +
b10100 $
b10100 *
#600000
b11100011110001010011000011000111 (
b11100011110001010011000011000111 -
b1101 &
b1101 ,
#610000
b1110 $
b1110 *
#620000
b10100100111100000011100101001 (
b10100100111100000011100101001 -
b11101 &
b11101 ,
#630000
b110 %
b110 +
b11100 $
b11100 *
#640000
b110011010011101010011101100110 (
b110011010011101010011101100110 -
#650000
b10011 %
b10011 +
b10000 $
b10000 *
#660000
b1111101010001110111100111111010 (
b1111101010001110111100111111010 -
b11110 &
b11110 ,
#670000
b11010 %
b11010 +
b10101 $
b10101 *
#680000
b10110 %
b10110 +
b10111 $
b10111 *
#690000
b11011011010001100001101010110110 (
b11011011010001100001101010110110 -
b110 &
b110 ,
#700000
b11100 %
b11100 +
b11101 $
b11101 *
#710000
b111111010110101001101101111110 (
b111111010110101001101101111110 -
b11000 &
b11000 ,
#720000
b1111 %
b1111 +
b11011 $
b11011 *
#730000
b1 %
b1 +
b11010 $
b11010 *
#740000
b110 %
b110 +
b1 $
b1 *
#750000
b10011010101101001000100000110101 (
b10011010101101001000100000110101 -
b10101 &
b10101 ,
#760000
b1 %
b1 +
b1001 $
b1001 *
#770000
b1011 %
b1011 +
b11000 $
b11000 *
#780000
b1010 %
b1010 +
b1100 $
b1100 *
#790000
b1010100100111101111110110101001 (
b1010100100111101111110110101001 -
b1000 &
b1000 ,
#800000
b1110 %
b1110 +
b1 $
b1 *
#810000
b10101001011111011010100101010 (
b10101001011111011010100101010 -
b11111 &
b11111 ,
#820000
b1101 %
b1101 +
b1010 $
b1010 *
#830000
b10111100110011111010100001111001 (
b10111100110011111010100001111001 -
b11000 &
b11000 ,
#840000
b1010 %
b1010 +
b1000 $
b1000 *
#850000
b111 %
b111 +
b1011 $
b1011 *
#860000
b1100010000101101010101111000100 (
b1100010000101101010101111000100 -
b11010 &
b11010 ,
#870000
b10010 %
b10010 +
b11001 $
b11001 *
#880000
b11000011001100111001000010000110 (
b11000011001100111001000010000110 -
b11111 &
b11111 ,
#890000
b11010 $
b11010 *
#900000
b1000010010011111100110110000100 (
b1000010010011111100110110000100 -
b11101 &
b11101 ,
#910000
b1010 %
b1010 +
b100 $
b100 *
#920000
b1110 %
b1110 +
b1 $
b1 *
#930000
b1111 %
b1111 +
b1011 $
b1011 *
#940000
b10101 %
b10101 +
b10110 $
b10110 *
#950000
b1000 %
b1000 +
b1011 $
b1011 *
#960000
b1001001001111100100010110010010 (
b1001001001111100100010110010010 -
b11011 &
b11011 ,
#970000
b1101 %
b1101 +
b1000 $
b1000 *
#980000
b11110 %
b11110 +
b10 $
b10 *
#990000
b11000 %
b11000 +
b1100 $
b1100 *
#1000000
b1 %
b1 +
b110 $
b110 *
#1010000
b10011 %
b10011 +
b11000 $
b11000 *
#1020000
b11110001011001101111101011100010 (
b11110001011001101111101011100010 -
#1030000
b100 $
b100 *
#1040000
b11011100000000110100010010111000 (
b11011100000000110100010010111000 -
b10010 &
b10010 ,
#1050000
b101 %
b101 +
b11001 $
b11001 *
#1060000
b1 %
b1 +
b1011 $
b1011 *
#1070000
b1010000110101011111100110100001 (
b1010000110101011111100110100001 -
b111 &
b111 ,
#1080000
b100 %
b100 +
b11111 $
b11111 *
#1090000
b1010011011101001001100010100 (
b1010011011101001001100010100 -
b10110 &
b10110 ,
#1100000
b10110 %
b10110 +
b10010 $
b10010 *
#1110000
b1101 %
b1101 +
b10101 $
b10101 *
#1130000
b111 %
b111 +
b100 $
b100 *
#1140000
b1001 %
b1001 +
b11001 $
b11001 *
#1150000
b10001 %
b10001 +
b1001 $
b1001 *
#1160000
b11010 %
b11010 +
b1010 $
b1010 *
#1170000
b11100 %
b11100 +
b11 $
b11 *
#1180000
b10110100010101011111001001101000 (
b10110100010101011111001001101000 -
b11110 &
b11110 ,
#1190000
b110 %
b110 +
b1111 $
b1111 *
#1200000
b100000011101101001000101000000 (
b100000011101101001000101000000 -
b11000 &
b11000 ,
#1210000
b10110 %
b10110 +
b1000 $
b1000 *
#1220000
b10100 %
b10100 +
b0 $
b0 *
#1230000
b11100 %
b11100 +
b10000 $
b10000 *
#1240000
b1010111011000011010100010101 (
b1010111011000011010100010101 -
b10 &
b10 ,
#1250000
b10111 %
b10111 +
b1 $
b1 *
#1260000
b110 %
b110 +
b1001 $
b1001 *
#1270000
b1101 %
b1101 +
b1 $
b1 *
#1280000
b10110010110110111101100101100 (
b10110010110110111101100101100 -
b111 &
b111 ,
#1290000
b10001 %
b10001 +
b1100 $
b1100 *
#1300000
b10111 %
b10111 +
b10110 $
b10110 *
#1310000
b101010101110001111011101010101 (
b101010101110001111011101010101 -
b11100 &
b11100 ,
#1320000
b0 %
b0 +
b0 $
b0 *
#1330000
b1101110100010101111010111011101 (
b1101110100010101111010111011101 -
b10100 &
b10100 ,
#1340000
b1011 %
b1011 +
b1101 $
b1101 *
#1350000
b11101 %
b11101 +
b11110 $
b11110 *
#1360000
b11 %
b11 +
b1111 $
b1111 *
#1370000
b10001 %
b10001 +
b11101 $
b11101 *
#1380000
b11110000000111010011010011100000 (
b11110000000111010011010011100000 -
b10101 &
b10101 ,
#1390000
b10010 %
b10010 +
b1101 $
b1101 *
#1400000
b10101001010111111100010001010010 (
b10101001010111111100010001010010 -
b1101 &
b1101 ,
#1410000
b110 %
b110 +
b100 $
b100 *
#1420000
b1011111010101100000100010111 (
b1011111010101100000100010111 -
b10000 &
b10000 ,
#1430000
b100 %
b100 +
b1010 $
b1010 *
#1440000
b10110000010100100000001001100000 (
b10110000010100100000001001100000 -
b11100 &
b11100 ,
#1450000
b1011 %
b1011 +
b11010 $
b11010 *
#1460000
b11001000001011000001100110010 (
b11001000001011000001100110010 -
b101 &
b101 ,
#1470000
b1001 %
b1001 +
b10 $
b10 *
#1480000
b100101111100100000001101001011 (
b100101111100100000001101001011 -
b11101 &
b11101 ,
#1490000
b111 %
b111 +
b11100 $
b11100 *
#1500000
b11011010000001011000101010110100 (
b11011010000001011000101010110100 -
b11001 &
b11001 ,
#1510000
b1100 %
b1100 +
b10000 $
b10000 *
#1520000
b10110101001000100100000001101010 (
b10110101001000100100000001101010 -
b111 &
b111 ,
#1530000
b1000 %
b1000 +
b10001 $
b10001 *
#1540000
b1100 %
b1100 +
b10011 $
b10011 *
#1550000
b1001 %
b1001 +
b100 $
b100 *
#1560000
b10100 %
b10100 +
b11111 $
b11111 *
#1570000
b10000 %
b10000 +
b11101 $
b11101 *
#1580000
b11101100101110010001101011011001 (
b11101100101110010001101011011001 -
b1001 &
b1001 ,
#1590000
b11100 %
b11100 +
b0 $
b0 *
#1600000
b1010 %
b1010 +
b11 $
b11 *
#1610000
b11101001111111001110100111010 (
b11101001111111001110100111010 -
b11101 &
b11101 ,
#1620000
b1011 %
b1011 +
b100 $
b100 *
#1630000
b10010 %
b10010 +
b10010 $
b10010 *
#1640000
b1110 %
b1110 +
b10000 $
b10000 *
#1650000
b110 %
b110 +
b11011 $
b11011 *
#1660000
b1111 %
b1111 +
b0 $
b0 *
#1670000
b11001 %
b11001 +
b1100 $
b1100 *
#1680000
b10000 %
b10000 +
b1111 $
b1111 *
#1690000
b10111 %
b10111 +
b1001 $
b1001 *
#1700000
b1001101110111010100110110011011 (
b1001101110111010100110110011011 -
b11000 &
b11000 ,
#1710000
b11000 %
b11000 +
b100 $
b100 *
#1720000
b10000 %
b10000 +
b110 $
b110 *
#1730000
b10100 %
b10100 +
b10101 $
b10101 *
#1740000
b1001 %
b1001 +
b10110 $
b10110 *
#1750000
b11011 %
b11011 +
b1 $
b1 *
#1760000
b11100010111011001101101011000101 (
b11100010111011001101101011000101 -
b10 &
b10 ,
#1770000
b1111 %
b1111 +
b10000 $
b10000 *
#1780000
b11110100110110000110111011101001 (
b11110100110110000110111011101001 -
b1111 &
b1111 ,
#1790000
b110 %
b110 +
b11000 $
b11000 *
#1800000
b10101 %
b10101 +
b1 $
b1 *
#1810000
b11110010100111000101111011100101 (
b11110010100111000101111011100101 -
b0 &
b0 ,
#1820000
b100 %
b100 +
b1000 $
b1000 *
#1830000
b10111 %
b10111 +
b1 $
b1 *
#1840000
b1101010100111111011100111010101 (
b1101010100111111011100111010101 -
b1 &
b1 ,
#1850000
b10000 %
b10000 +
b1000 $
b1000 *
#1860000
b11111000110111000100100011110001 (
b11111000110111000100100011110001 -
b1111 &
b1111 ,
#1870000
b1110 %
b1110 +
b11101 $
b11101 *
#1880000
b11010100101101011110011010101001 (
b11010100101101011110011010101001 -
b11100 &
b11100 ,
#1890000
b11011 %
b11011 +
b1111 $
b1111 *
#1900000
b11001 %
b11001 +
b1010 $
b1010 *
#1910000
b101 %
b101 +
b10011 $
b10011 *
#1920000
b11001 %
b11001 +
b10111 $
b10111 *
#1930000
b110001011111000000011101100010 (
b110001011111000000011101100010 -
b10001 &
b10001 ,
#1940000
b1010 %
b1010 +
b100 $
b100 *
#1950000
b101 %
b101 +
b11001 $
b11001 *
#1960000
b1 %
b1 +
b1001 $
b1001 *
#1970000
b1101 %
b1101 +
b11011 $
b11011 *
#1980000
b11010001010010000010000010100010 (
b11010001010010000010000010100010 -
b110 &
b110 ,
#1990000
b1010 %
b1010 +
b11101 $
b11101 *
#2000000
b10111101100001101111010001111011 (
b10111101100001101111010001111011 -
b10000 &
b10000 ,
#2010000
b11000 %
b11000 +
b101 $
b101 *
#2020000
b10001110011001001101100100011 (
b10001110011001001101100100011 -
b11100 &
b11100 ,
#2030000
b1000 %
b1000 +
b11001 $
b11001 *
#2040000
b10011 %
b10011 +
b1110 $
b1110 *
#2050000
b1101010000110100110000111010100 (
b1101010000110100110000111010100 -
b1110 &
b1110 ,
#2060000
b11001 %
b11001 +
b11001 $
b11001 *
#2070000
b10101 %
b10101 +
b10100 $
b10100 *
#2080000
b1011100101001001100000010 (
b1011100101001001100000010 -
b11001 &
b11001 ,
#2090000
b101 %
b101 +
b10101 $
b10101 *
#2100000
b1011100011110010101000110111000 (
b1011100011110010101000110111000 -
b10 &
b10 ,
#2110000
b1101 %
b1101 +
b1000 $
b1000 *
#2120000
b10000 %
b10000 +
#2130000
b11011 %
b11011 +
b1100 $
b1100 *
#2140000
b10000110111010111011011000001101 (
b10000110111010111011011000001101 -
b101 &
b101 ,
#2150000
b1101 %
b1101 +
b10000 $
b10000 *
#2160000
b10000 %
b10000 +
b11100 $
b11100 *
#2170000
b11010000110011110110101010100001 (
b11010000110011110110101010100001 -
b10000 &
b10000 ,
#2180000
b10101 %
b10101 +
b1101 $
b1101 *
#2190000
b10100 %
b10100 +
b11101 $
b11101 *
#2200000
b11011100010000110000100010111000 (
b11011100010000110000100010111000 -
b11100 &
b11100 ,
#2210000
b11010 %
b11010 +
b11110 $
b11110 *
#2220000
b11001001110010111011110010010011 (
b11001001110010111011110010010011 -
b111 &
b111 ,
#2230000
b10111 %
b10111 +
b10101 $
b10101 *
#2240000
b11001 %
b11001 +
b11 $
b11 *
#2250000
b10001111011000111110010000011110 (
b10001111011000111110010000011110 -
b1000 &
b1000 ,
#2260000
b11010 %
b11010 +
b10000 $
b10000 *
#2270000
b1010101100001100001111110101011 (
b1010101100001100001111110101011 -
b11001 &
b11001 ,
#2280000
b1111 %
b1111 +
#2290000
b1000110110101101010011110001101 (
b1000110110101101010011110001101 -
b101 &
b101 ,
#2300000
b11100 %
b11100 +
b1011 $
b1011 *
#2310000
b1100100101111000110100011001 (
b1100100101111000110100011001 -
b100 &
b100 ,
#2320000
b11110 %
b11110 +
b101 $
b101 *
#2330000
b100 %
b100 +
b11000 $
b11000 *
#2340000
b11001101000111010101000010011010 (
b11001101000111010101000010011010 -
b110 &
b110 ,
#2350000
b101 %
b101 +
#2360000
b1100001110110111101010111000011 (
b1100001110110111101010111000011 -
b11010 &
b11010 ,
#2370000
b1100 %
b1100 +
b10010 $
b10010 *
#2380000
b1011 %
b1011 +
b11 $
b11 *
#2390000
b1000100100000111010110110001001 (
b1000100100000111010110110001001 -
b10010 &
b10010 ,
#2400000
b11011 %
b11011 +
b1111 $
b1111 *
#2410000
b101 %
b101 +
b1000 $
b1000 *
#2420000
b11011 %
b11011 +
b1011 $
b1011 *
#2430000
b1000001001011011111110110000010 (
b1000001001011011111110110000010 -
b11101 &
b11101 ,
#2440000
b10111 %
b10111 +
b100 $
b100 *
#2450000
b10111100111000110010100001111001 (
b10111100111000110010100001111001 -
b10010 &
b10010 ,
#2460000
b10110 %
b10110 +
#2470000
b10010111010110011000100000101110 (
b10010111010110011000100000101110 -
b0 &
b0 ,
#2480000
b10001 %
b10001 +
b1100 $
b1100 *
#2490000
b11100 %
b11100 +
b11100 $
b11100 *
#2500000
b1011 %
b1011 +
b1 $
b1 *
#2510000
b1111 %
b1111 +
b1001 $
b1001 *
#2520000
b10011 %
b10011 +
b10000 $
b10000 *
#2530000
b1101011000110111010100011010 (
b1101011000110111010100011010 -
b10 &
b10 ,
#2540000
b10111 %
b10111 +
b10001 $
b10001 *
#2550000
b1100110100001100001110111001101 (
b1100110100001100001110111001101 -
b10001 &
b10001 ,
#2560000
b11100 %
b11100 +
b101 $
b101 *
#2570000
b10010101010000011101011000101010 (
b10010101010000011101011000101010 -
b1100 &
b1100 ,
#2580000
b10111 %
b10111 +
#2590000
b11101 %
b11101 +
b11110 $
b11110 *
#2600000
b10111010011000000011100001110100 (
b10111010011000000011100001110100 -
b1000 &
b1000 ,
#2610000
b110 %
b110 +
b10000 $
b10000 *
#2620000
b11100010101110100000000011000101 (
b11100010101110100000000011000101 -
#2630000
b10110 %
b10110 +
b11110 $
b11110 *
#2640000
b1011 %
b1011 +
b11011 $
b11011 *
#2650000
b10100 %
b10100 +
b1111 $
b1111 *
#2660000
b11101010011101100010011011010100 (
b11101010011101100010011011010100 -
b110 &
b110 ,
#2670000
b1011 %
b1011 +
b1011 $
b1011 *
#2680000
b1000110100010110110000110001101 (
b1000110100010110110000110001101 -
b10100 &
b10100 ,
#2690000
b101 %
b101 +
b1 $
b1 *
#2700000
b0 %
b0 +
b1001 $
b1001 *
#2710000
b11011100001010101111100110111 (
b11011100001010101111100110111 -
b11100 &
b11100 ,
#2720000
b10011 %
b10011 +
b11000 $
b11000 *
#2730000
b11000001111111100001100110000 (
b11000001111111100001100110000 -
#2740000
b0 %
b0 +
b10000 $
b10000 *
#2750000
b1 %
b1 +
b11000 $
b11000 *
#2760000
b11111 %
b11111 +
#2770000
b1101 %
b1101 +
b11010 $
b11010 *
#2780000
b10011000110101110011100000110001 (
b10011000110101110011100000110001 -
b1011 &
b1011 ,
#2790000
b1100 %
b1100 +
b10010 $
b10010 *
#2800000
b0 %
b0 +
b10101 $
b10101 *
#2810000
b11000000011000100000001010000000 (
b11000000011000100000001010000000 -
b10100 &
b10100 ,
#2820000
b11 %
b11 +
b10011 $
b10011 *
#2830000
b11000 %
b11000 +
b11100 $
b11100 *
#2840000
b11 %
b11 +
b11111 $
b11111 *
#2850000
b10 %
b10 +
b11000 $
b11000 *
#2860000
b111 $
b111 *
#2870000
b10010010011111111010010000100100 (
b10010010011111111010010000100100 -
b111 &
b111 ,
#2880000
b1000 %
b1000 +
b11011 $
b11011 *
#2890000
b11010 %
b11010 +
b10101 $
b10101 *
#2900000
b10101100000001011010000001011000 (
b10101100000001011010000001011000 -
b10 &
b10 ,
#2910000
b11 %
b11 +
b10000 $
b10000 *
#2920000
b1110101001111000001011111101010 (
b1110101001111000001011111101010 -
b101 &
b101 ,
#2930000
b10100 %
b10100 +
b110 $
b110 *
#2940000
b1000 %
b1000 +
b1000 $
b1000 *
#2950000
b10101 %
b10101 +
b11000 $
b11000 *
#2960000
b11011 %
b11011 +
b11 $
b11 *
#2970000
b10000 $
b10000 *
#2980000
b11000 %
b11000 +
#2990000
b1 %
b1 +
b110 $
b110 *
#3000000
b1111 %
b1111 +
b10101 $
b10101 *
#3010000
b10011 %
b10011 +
b11110 $
b11110 *
#3020000
b101100010101110111100101011000 (
b101100010101110111100101011000 -
b1001 &
b1001 ,
#3030000
b11 %
b11 +
b10101 $
b10101 *
#3040000
b111111001001011110111101111110 (
b111111001001011110111101111110 -
b100 &
b100 ,
#3050000
b1111 %
b1111 +
b10110 $
b10110 *
#3060000
b10 %
b10 +
b0 $
b0 *
#3070000
b10111 %
b10111 +
b101 $
b101 *
#3080000
b11000 %
b11000 +
b10101 $
b10101 *
#3090000
b10101000010011100101100001010000 (
b10101000010011100101100001010000 -
b1100 &
b1100 ,
#3100000
b11100 %
b11100 +
b10001 $
b10001 *
#3110000
b10000111001011010010110000001110 (
b10000111001011010010110000001110 -
b1111 &
b1111 ,
#3120000
b10010 %
b10010 +
b1001 $
b1001 *
#3130000
b1010101010111000000111110101010 (
b1010101010111000000111110101010 -
b101 &
b101 ,
#3140000
b10 %
b10 +
b1000 $
b1000 *
#3150000
b11011101000100010001101010111010 (
b11011101000100010001101010111010 -
b10011 &
b10011 ,
#3160000
b1011 %
b1011 +
b11011 $
b11011 *
#3170000
b111000111001100001001101110001 (
b111000111001100001001101110001 -
b1100 &
b1100 ,
#3180000
b1 %
b1 +
b11110 $
b11110 *
#3190000
b10001 %
b10001 +
b11111 $
b11111 *
#3200000
b10111111010100111011010001111110 (
b10111111010100111011010001111110 -
b11001 &
b11001 ,
#3210000
b10100 $
b10100 *
#3220000
b100 %
b100 +
b111 $
b111 *
#3230000
b11001 %
b11001 +
b11011 $
b11011 *
#3240000
b10001 %
b10001 +
b10111 $
b10111 *
#3250000
b10001110001110000100000100 (
b10001110001110000100000100 -
b1111 &
b1111 ,
#3260000
b11100 %
b11100 +
b10010 $
b10010 *
#3270000
b11111 %
b11111 +
b100 $
b100 *
#3280000
b101101010011011001101101011010 (
b101101010011011001101101011010 -
b10011 &
b10011 ,
#3290000
b11110 %
b11110 +
b0 $
b0 *
#3300000
b1110001001100101011101111100010 (
b1110001001100101011101111100010 -
b11011 &
b11011 ,
#3310000
b11111 %
b11111 +
b10 $
b10 *
#3320000
b1000000101111100101100010000 (
b1000000101111100101100010000 -
b11111 &
b11111 ,
#3330000
b11101 %
b11101 +
b10010 $
b10010 *
#3340000
b10100 %
b10100 +
b10100 $
b10100 *
#3350000
b1100 %
b1100 +
b10011 $
b10011 *
#3360000
b10101 %
b10101 +
b11011 $
b11011 *
#3370000
b10100 $
b10100 *
#3380000
b11010011111111100011011010100111 (
b11010011111111100011011010100111 -
b10010 &
b10010 ,
#3390000
b100 %
b100 +
b1 $
b1 *
#3400000
b11010 %
b11010 +
b1001 $
b1001 *
#3410000
b10101 %
b10101 +
b11111 $
b11111 *
#3420000
b10001001000001000010111000010010 (
b10001001000001000010111000010010 -
b1011 &
b1011 ,
#3430000
b1110 %
b1110 +
b10111 $
b10111 *
#3440000
b11101101000110110101000011011010 (
b11101101000110110101000011011010 -
b0 &
b0 ,
#3450000
b1100 %
b1100 +
b10 $
b10 *
#3460000
b1111000111100101000100011110 (
b1111000111100101000100011110 -
b11010 &
b11010 ,
#3470000
b1011 %
b1011 +
b1001 $
b1001 *
#3480000
b11110 %
b11110 +
b1110 $
b1110 *
#3490000
b11000101110010110101010010001011 (
b11000101110010110101010010001011 -
b101 &
b101 ,
#3500000
b10111 %
b10111 +
b10010 $
b10010 *
#3510000
b1110 %
b1110 +
b1 $
b1 *
#3520000
b1100110100110010000011111001101 (
b1100110100110010000011111001101 -
b10101 &
b10101 ,
#3530000
b10100 %
b10100 +
b100 $
b100 *
#3540000
b11110001101000110010111011100011 (
b11110001101000110010111011100011 -
b11010 &
b11010 ,
#3550000
b10011 %
b10011 +
b1100 $
b1100 *
#3560000
b11101 %
b11101 +
b11100 $
b11100 *
#3570000
b1111111110110111011001111111111 (
b1111111110110111011001111111111 -
b1111 &
b1111 ,
#3580000
b1011 %
b1011 +
b11000 $
b11000 *
#3590000
b10011 %
b10011 +
b11011 $
b11011 *
#3600000
b11110011011000011100101011100110 (
b11110011011000011100101011100110 -
b11011 &
b11011 ,
#3610000
b1010 %
b1010 +
b1001 $
b1001 *
#3620000
b1001011000111001110100110010110 (
b1001011000111001110100110010110 -
b11000 &
b11000 ,
#3630000
b1110 %
b1110 +
#3640000
b10110 %
b10110 +
b110 $
b110 *
#3650000
b10101 %
b10101 +
b1111 $
b1111 *
#3660000
b1111 %
b1111 +
b11100 $
b11100 *
#3670000
b10100 %
b10100 +
b1001 $
b1001 *
#3680000
b1101111110011111111000111011111 (
b1101111110011111111000111011111 -
b1101 &
b1101 ,
#3690000
b10000 %
b10000 +
b1101 $
b1101 *
#3700000
b100 %
b100 +
b10001 $
b10001 *
#3710000
b11011110011110110100000110 (
b11011110011110110100000110 -
b11001 &
b11001 ,
#3720000
b11111 %
b11111 +
b1010 $
b1010 *
#3730000
b10000 %
b10000 +
b100 $
b100 *
#3740000
b11110 %
b11110 +
b10000 $
b10000 *
#3750000
b1101011111110000010001111010111 (
b1101011111110000010001111010111 -
b1001 &
b1001 ,
#3760000
b1101 %
b1101 +
b1 $
b1 *
#3770000
b11010 %
b11010 +
b10011 $
b10011 *
#3780000
b10111 %
b10111 +
b1110 $
b1110 *
#3790000
b11001110000000111110110010011100 (
b11001110000000111110110010011100 -
b11101 &
b11101 ,
#3800000
b100 %
b100 +
b1111 $
b1111 *
#3810000
b1001 %
b1001 +
b10 $
b10 *
#3820000
b1100011001011110000011111000110 (
b1100011001011110000011111000110 -
b1101 &
b1101 ,
#3830000
b0 %
b0 +
b1010 $
b1010 *
#3840000
b1000 %
b1000 +
b10000 $
b10000 *
#3850000
b11011 %
b11011 +
b10001 $
b10001 *
#3860000
b11000 %
b11000 +
b11101 $
b11101 *
#3870000
b110 %
b110 +
b10111 $
b10111 *
#3880000
b10111 %
b10111 +
b100 $
b100 *
#3890000
b10011 %
b10011 +
b1101 $
b1101 *
#3900000
b11001 %
b11001 +
b1110 $
b1110 *
#3910000
b1000000111110110100111110000001 (
b1000000111110110100111110000001 -
b11001 &
b11001 ,
#3920000
b1111 %
b1111 +
b10001 $
b10001 *
#3930000
b10000111100010101000100000001111 (
b10000111100010101000100000001111 -
b11101 &
b11101 ,
#3940000
b1001 %
b1001 +
b10011 $
b10011 *
#3950000
b101110011100100010100101011100 (
b101110011100100010100101011100 -
b11010 &
b11010 ,
#3960000
b10011 %
b10011 +
b1001 $
b1001 *
#3970000
b10111100000111000000111001111000 (
b10111100000111000000111001111000 -
b11000 &
b11000 ,
#3980000
b101 %
b101 +
b11001 $
b11001 *
#3990000
b1100 %
b1100 +
b10110 $
b10110 *
#4000000
b0 %
b0 +
b11010 $
b11010 *
#4010000
b10110110011010100101100001101100 (
b10110110011010100101100001101100 -
b1000 &
b1000 ,
#4020000
b11101 %
b11101 +
b0 $
b0 *
#4030000
b11010 %
b11010 +
#4040000
b10100110010010010000110001001100 (
b10100110010010010000110001001100 -
b0 &
b0 ,
#4050000
b10001 %
b10001 +
b10001 $
b10001 *
#4060000
b10011 %
b10011 +
b101 $
b101 *
#4070000
b1111110010110110101001111111100 (
b1111110010110110101001111111100 -
#4080000
b1 %
b1 +
b1000 $
b1000 *
#4090000
b11 %
b11 +
b111 $
b111 *
#4100000
b100 %
b100 +
b0 $
b0 *
#4110000
b1000111001011011111101110001110 (
b1000111001011011111101110001110 -
b10001 &
b10001 ,
#4120000
b1000 %
b1000 +
b11110 $
b11110 *
#4130000
b11111 %
b11111 +
b1010 $
b1010 *
