Phase 2/1bit/counter.v
module counter(
    input CLOCK,
    input INIT,
    input MISS,
    output [15:0] MISSES
);

reg [15:0] temp;

always @(posedge CLOCK) begin
    if (INIT) begin
        temp <= 16'b0000000000000000;
    end else begin
        if (MISS) begin
            if (temp == 16'b111111111111111) begin
                temp <= 16'b0000000000000000;
            end else begin
                temp <= temp + 1;
            end
        end
    end
end

assign MISSES = temp;

endmodule

Phase 2/1bit/comparator.v
module comparator(
    input CLOCK,
    input INIT,
    input OUTCOME,
    input [2:0] ADDR,
    input PREDICTION,
    output [2:0] ADDR_W,
    output MISS
);

assign MISS = OUTCOME ^ PREDICTION;
assign ADDR_W = ADDR;

endmodule

Phase 2/1bit/Multiplexer.v
module Multiplexer(
    input wire A,
    input wire B,
    input wire [2:0] ADDR,
    output reg OUTPUT
);

always @* begin
    case (ADDR)
        3'b001: OUTPUT = A;
        3'b010: OUTPUT = B;
        default: OUTPUT = 1'b0;
    endcase
end

endmodule

Phase2/1bit/counterOne.v
module counterOne(
    input CLOCK,
    input INIT,
    input OUTCOME,
    input MISS,
    output wire PREDICTION
);

reg count;

always @(posedge CLOCK) begin
    if (INIT) begin
        count <= 1'b0;
    end else begin
        if (MISS) begin
            count <= ~count;
        end
    end
end

assign PREDICTION = count;

endmodule

Phase 2/1bit/demultiplexer.v
module demultiplexer(
    output wire out0,
    output wire miss0,
    output wire out1,
    output wire miss1,
    input wire [2:0] ADDR,
    input wire OUTCOME,
    input wire MISS
);

assign out0 = (ADDR == 3'b001) ? OUTCOME : 1'b0;
assign miss0 = (ADDR == 3'b001) ? MISS : 1'b0;
assign out1 = (ADDR == 3'b010) ? OUTCOME : 1'b0;
assign miss1 = (ADDR == 3'b010) ? MISS : 1'b0;

endmodule

Phase 2/1bit/OneCounterPredictor.v
module OneCounterPredictor(
    input wire CLOCK,
    input wire INIT,
    input wire [2:0] ADDR,
    input wire OUTCOME,
    output wire PREDICTION,
    output wire [15:0] MISSES
);

wire [15:0] miss_in;
wire [2:0] addr_out;
wire demout0;
wire demout1;
wire demmiss0;
wire demmiss1;
wire A;
wire B;
wire PREDICTION_wire;

demultiplexer demux (
    .out0(demout0),
    .miss0(demmiss0),
    .out1(demout1),
    .miss1(demmiss1),
    .ADDR(ADDR),
    .OUTCOME(OUTCOME),
    .MISS(miss_in[0])
);

counterOne firstCount (
    .CLOCK(CLOCK),
    .INIT(INIT),
    .OUTCOME(demout0),
    .MISS(demmiss0),
    .PREDICTION(A)
);

counterOne secondCount (
    .CLOCK(CLOCK),
    .INIT(INIT),
    .OUTCOME(demout1),
    .MISS(demmiss1),
    .PREDICTION(B)
);

Multiplexer mux (
    .A(A),
    .B(B),
    .ADDR(ADDR),
    .OUTPUT(PREDICTION_wire)
);

comparator comp (
    .CLOCK(CLOCK),
    .INIT(INIT),
    .OUTCOME(OUTCOME),
    .ADDR(ADDR),
    .PREDICTION(PREDICTION_wire),
    .ADDR_W(addr_out),
    .MISS(miss_in[0])
);

counter countM (
    .CLOCK(CLOCK),
    .INIT(INIT),
    .MISS(miss_in[0]),
    .MISSES(MISSES)
);

assign PREDICTION = PREDICTION_wire;
assign miss_in[15:1] = 16'b0;

endmodule

Phase2/1bit/tb_OneCounterPredictorTest.v
module tb_OneCounterPredictorTest;
  // Entity declaration
  // entity tb_OneCounterPredictorTest is
  // end tb_OneCounterPredictorTest;

  // Component declaration for the Unit Under Test (UUT)
  // component OneCounterPredictor
  //   Port(
  //     CLOCK : in std_logic;
  //     INIT : in std_logic;
  //     ADDR : in std_logic_vector (2 downto 0);
  //     OUTCOME : in std_logic;
  //     PREDICTION : out std_logic;
  //     MISSES : out std_logic_vector (15 downto 0)
  //   );
  // end component;

  // Inputs
  reg CLOCK = 1'b0;
  reg INIT = 1'b0;
  reg [2:0] ADDR = 3'b000;
  reg OUTCOME = 1'b0;

  // Outputs
  wire PREDICTION;
  wire [15:0] MISSES;

  // Constants
//   real clk_period = 10 ns;

  // Instantiate the Unit Under Test (UUT)
  OneCounterPredictor uut (
    .CLOCK(CLOCK),
    .INIT(INIT),
    .ADDR(ADDR),
    .OUTCOME(OUTCOME),
    .PREDICTION(PREDICTION),
    .MISSES(MISSES)
  );

  // clk process definition
  always begin
    #5;
    CLOCK <= 1;
    #5;
    CLOCK <= 0;
  end

  // Stimulus process
  initial begin
    // wait for 15 ns;
    #15;

    INIT <= 1'b1;
    // wait for 10 ns;
    #10;
    INIT <= 1'b0;

    ADDR <= 3'b001;
    OUTCOME <= 1'b1;
    // wait for 10 ns;
    #10;

    ADDR <= 3'b010;
    OUTCOME <= 1'b1;
    // wait for 10 ns;
    #10;

    ADDR <= 3'b001;
    OUTCOME <= 1'b0;
    // wait for 10 ns;
    #10;

    ADDR <= 3'b001;
    OUTCOME <= 1'b0;
    // wait for 10 ns;
    #10;

    ADDR <= 3'b001;
    OUTCOME <= 1'b0;
    // wait for 10 ns;
    #10;

    ADDR <= 3'b010;
    OUTCOME <= 1'b0;
    // wait for 10 ns;
    #10;

    ADDR <= 3'b001;
    OUTCOME <= 1'b1;
    // wait for 10 ns;
    #10;

    ADDR <= 3'b001;
    OUTCOME <= 1'b1;
    // wait for 10 ns;
    #10;

    ADDR <= 3'b001;
    OUTCOME <= 1'b0;
    // wait for 10 ns;
    #10;

    ADDR <= 3'b001;
    OUTCOME <= 1'b0;
    // wait for 10 ns;
    #10;

    ADDR <= 3'b010;
    OUTCOME <= 1'b1;
    // wait for 10 ns;
    #10;

    ADDR <= 3'b001;
    OUTCOME <= 1'b0;
    // wait for 10 ns;
    #10;

    ADDR <= 3'b001;
    OUTCOME <= 1'b0;
    // wait for 10 ns;
    #10;

    ADDR <= 3'b010;
    OUTCOME <= 1'b1;
    // wait for 10 ns;
    #10;

    ADDR <= 3'b010;
    OUTCOME <= 1'b0;
    // wait for 10 ns;
    #10;

    ADDR <= 3'b001;
    OUTCOME <= 1'b0;
    // wait for 10 ns;
    #10;

    ADDR <= 3'b001;
    OUTCOME <= 1'b1;
    // wait for 10 ns;
    #10;

    ADDR <= 3'b001;
    OUTCOME <= 1'b0;
    // wait for 10 ns;
    #10;

    ADDR <= 3'b001;
    OUTCOME <= 1'b0;
    // wait for 10 ns;
    #10;

    $finish;
  end
  
  // Dump VCD file for GTKWave
  initial begin
    $dumpfile("tb_OneCounterPredictorTest.vcd");
    $dumpvars;
  end
  
  // Simulation end
  initial begin
    #150;
    $finish;
  end
endmodule

Phase 2/1bit/tb_OneCounterPredictorTest.vcd
$date
	Wed Jun 28 08:25:32 2023
$end
$version
	Icarus Verilog
$end
$timescale
	1s
$end
$scope module tb_OneCounterPredictorTest $end
$var wire 1 ! PREDICTION $end
$var wire 16 " MISSES [15:0] $end
$var reg 3 # ADDR [2:0] $end
$var reg 1 $ CLOCK $end
$var reg 1 % INIT $end
$var reg 1 & OUTCOME $end
$scope module uut $end
$var wire 3 ' ADDR [2:0] $end
$var wire 1 $ CLOCK $end
$var wire 1 % INIT $end
$var wire 1 & OUTCOME $end
$var wire 1 ! PREDICTION $end
$var wire 16 ( miss_in [15:0] $end
$var wire 1 ) demout1 $end
$var wire 1 * demout0 $end
$var wire 1 + demmiss1 $end
$var wire 1 , demmiss0 $end
$var wire 3 - addr_out [2:0] $end
$var wire 1 . PREDICTION_wire $end
$var wire 16 / MISSES [15:0] $end
$var wire 1 0 B $end
$var wire 1 1 A $end
$scope module comp $end
$var wire 3 2 ADDR [2:0] $end
$var wire 3 3 ADDR_W [2:0] $end
$var wire 1 $ CLOCK $end
$var wire 1 % INIT $end
$var wire 1 4 MISS $end
$var wire 1 & OUTCOME $end
$var wire 1 . PREDICTION $end
$upscope $end
$scope module countM $end
$var wire 1 $ CLOCK $end
$var wire 1 % INIT $end
$var wire 1 5 MISS $end
$var wire 16 6 MISSES [15:0] $end
$var reg 16 7 temp [15:0] $end
$upscope $end
$scope module demux $end
$var wire 3 8 ADDR [2:0] $end
$var wire 1 9 MISS $end
$var wire 1 & OUTCOME $end
$var wire 1 ) out1 $end
$var wire 1 * out0 $end
$var wire 1 + miss1 $end
$var wire 1 , miss0 $end
$upscope $end
$scope module firstCount $end
$var wire 1 $ CLOCK $end
$var wire 1 % INIT $end
$var wire 1 , MISS $end
$var wire 1 * OUTCOME $end
$var wire 1 1 PREDICTION $end
$var reg 1 : count $end
$upscope $end
$scope module mux $end
$var wire 1 1 A $end
$var wire 3 ; ADDR [2:0] $end
$var wire 1 0 B $end
$var reg 1 . OUTPUT $end
$upscope $end
$scope module secondCount $end
$var wire 1 $ CLOCK $end
$var wire 1 % INIT $end
$var wire 1 + MISS $end
$var wire 1 ) OUTCOME $end
$var wire 1 0 PREDICTION $end
$var reg 1 < count $end
$upscope $end
$upscope $end
$upscope $end
$enddefinitions $end
#0
$dumpvars
x<
b0 ;
x:
09
b0 8
bx 7
bx 6
05
04
b0 3
b0 2
x1
x0
bx /
0.
b0 -
0,
0+
0*
0)
b0 (
b0 '
0&
0%
0$
b0 #
bx "
0!
$end
#5
1$
#10
0$
#15
b0 "
b0 /
b0 6
b0 7
00
0<
01
0:
1$
1%
#20
0$
#25
1,
15
19
b1 (
14
1*
1$
1&
b1 -
b1 3
b1 #
b1 '
b1 2
b1 8
b1 ;
0%
#30
0$
#35
05
09
b0 (
04
1!
1.
b1 "
b1 /
b1 6
b1 7
10
1<
0*
0,
1)
0+
1$
b10 -
b10 3
b10 #
b10 '
b10 2
b10 8
b10 ;
#40
0$
#45
0)
0!
0.
1$
0&
b1 -
b1 3
b1 #
b1 '
b1 2
b1 8
b1 ;
#50
0$
#55
1$
#60
0$
#65
1$
#70
0$
#75
1+
15
19
b1 (
14
1!
1.
1$
b10 -
b10 3
b10 #
b10 '
b10 2
b10 8
b10 ;
#80
0$
#85
05
09
b0 (
04
11
1:
b10 "
b10 /
b10 6
b10 7
1*
0,
0+
1!
1.
1$
1&
b1 -
b1 3
b1 #
b1 '
b1 2
b1 8
b1 ;
#90
0$
#95
1$
#100
0$
#105
1,
15
19
b1 (
14
0*
1$
0&
#110
0$
#115
0,
05
09
b0 (
04
0!
0.
b11 "
b11 /
b11 6
b11 7
01
0:
1$
#120
0$
#125
1)
1!
1.
1$
1&
b10 -
b10 3
b10 #
b10 '
b10 2
b10 8
b10 ;
#130
0$
#135
0)
0!
0.
1$
0&
b1 -
b1 3
b1 #
b1 '
b1 2
b1 8
b1 ;
